rossetta_fastapi/__init__.py
rossetta_fastapi/crypto.py
rossetta_fastapi/middleware.py
rossetta_fastapi/session.py
rossetta_fastapi-0.1.5.dist-info/licenses/LICENSE
rossetta_fastapi-0.1.5.dist-info/METADATA
rossetta_fastapi-0.1.5.dist-info/WHEEL
rossetta_fastapi-0.1.5.dist-info/top_level.txt
rossetta_fastapi-0.1.5.dist-info/RECORD
